clip2imgur/.DS_Store
clip2imgur/__init__.py
clip2imgur/clip2imgur.py
clip2imgur/__pycache__/__init__.cpython-310.pyc
clip2imgur/__pycache__/clip2imgur.cpython-310.pyc
clip2imgur-0.9.4.dist-info/METADATA
clip2imgur-0.9.4.dist-info/WHEEL
clip2imgur-0.9.4.dist-info/entry_points.txt
clip2imgur-0.9.4.dist-info/top_level.txt
clip2imgur-0.9.4.dist-info/RECORD
