Metadata-Version: 2.1
Name: clip2imgur
Version: 0.9.4
Summary: A simple CLI that uploads your image in the clipboard to Imgur.
Home-page: https://github.com/xiaohk/clip2imgur
Author: Jay Wang
Author-email: jayw@zijie.wang
License: MIT license
Keywords: Imgur,CLI,Image,Clipboard
Platform: Linux
Platform: Mac OS X
Platform: Windows
Classifier: License :: OSI Approved :: MIT License
Classifier: Programming Language :: Python
Classifier: Programming Language :: Python :: 3
Classifier: Programming Language :: Python :: 3.6
Classifier: Programming Language :: Python :: 3.7
Classifier: Programming Language :: Python :: 3.8
Classifier: Programming Language :: Python :: 3.9
Classifier: Framework :: Jupyter
Classifier: Framework :: Jupyter :: JupyterLab
Classifier: Framework :: Jupyter :: JupyterLab :: 3
Requires-Python: >=3.6
Requires-Dist: pyobjc-framework-Cocoa
Requires-Dist: pyperclip
Requires-Dist: rich
Requires-Dist: requests
